LICENSE
passoperator/__init__.py
passoperator/daemon.py
passoperator/git.py
passoperator/gpg.py
passoperator/locks.py
passoperator/secret.py
passoperator/utils.py
pass_operator-0.4.8.dist-info/LICENSE
pass_operator-0.4.8.dist-info/METADATA
pass_operator-0.4.8.dist-info/WHEEL
pass_operator-0.4.8.dist-info/entry_points.txt
pass_operator-0.4.8.dist-info/RECORD
