Metadata-Version: 2.1
Name: pass-operator
Version: 0.4.8
Summary: A Kubernetes operator that syncs and decrypts secrets from pass store git repositories
License: GPL-3.0-or-later
Keywords: python,kubernetes,secrets,operator,pass
Author: Emma Doyle
Author-email: emma@premiscale.com
Maintainer: Emma Doyle
Maintainer-email: emma@premiscale.com
Requires-Python: >=3.10,<4.0
Classifier: License :: OSI Approved :: GNU General Public License v3 or later (GPLv3+)
Classifier: Programming Language :: Python :: 3
Classifier: Programming Language :: Python :: 3.10
Classifier: Programming Language :: Python :: 3.11
Classifier: Programming Language :: Python :: 3.12
Requires-Dist: attrs (>=23.2.0,<24.0.0)
Requires-Dist: cattrs (>=23.2.3,<24.0.0)
Requires-Dist: gitpython (>=3.1.43,<4.0.0)
Requires-Dist: kopf (>=1.37.2,<2.0.0)
Requires-Dist: kubernetes (>=29.0.0,<30.0.0)
Requires-Dist: pyhumps (>=3.8.0,<4.0.0)
Requires-Dist: python-gnupg (>=0.5.2,<0.6.0)
